vlad_age/__init__.py
vlad_age/age.py
vlad_new-1.0.0.dist-info/METADATA
vlad_new-1.0.0.dist-info/WHEEL
vlad_new-1.0.0.dist-info/top_level.txt
vlad_new-1.0.0.dist-info/RECORD
