Metadata-Version: 2.1
Name: vlad-new
Version: 1.0.0
Summary: This is my first module
Home-page: UNKNOWN
Author: KhimichVladyslav
Author-email: khimich.vladyslav@gmail.com
License: UNKNOWN
Keywords: example python
Platform: UNKNOWN
Classifier: Programming Language :: Python :: 3.11
Classifier: License :: OSI Approved :: MIT License
Classifier: Operating System :: OS Independent
Requires-Python: >=3.7
Requires-Dist: requests (>=2.25.1)
